terminal_space-0.2.0.dist-info/METADATA
terminal_space-0.2.0.dist-info/WHEEL
tspace/__init__.py
tspace/client/__init__.py
tspace/client/app.py
tspace/client/game.py
tspace/client/instant_cmd.py
tspace/client/logging.py
tspace/client/models.py
tspace/client/port_prompt.py
tspace/client/prompts.py
tspace/client/scene/__init__.py
tspace/client/scene/game.py
tspace/client/scene/main_menu.py
tspace/client/sector_prompt.py
tspace/client/session.py
tspace/client/stream.py
tspace/client/terminal_text_area.py
tspace/client/tests/__init__.py
tspace/client/tests/test_stream.py
tspace/client/theme/__init__.py
tspace/client/theme/api.py
tspace/client/theme/tw2002.py
tspace/client/twbuffer.py
tspace/client/ui/__init__.py
tspace/client/ui/button.py
tspace/client/ui/draw.py
tspace/client/ui/dynamic_label.py
tspace/client/ui/menu.py
tspace/client/ui/starfield.py
tspace/client/ui/stat_frame.py
tspace/client/ui/warp.py
tspace/client/util.py
tspace/client_app.py
tspace/json_types/__init__.py
tspace/server/__init__.py
tspace/server/builders/__init__.py
tspace/server/builders/countermeasures.py
tspace/server/builders/planets.py
tspace/server/builders/players.py
tspace/server/builders/ports.py
tspace/server/builders/sectors.py
tspace/server/builders/ships.py
tspace/server/builders/weapons.py
tspace/server/config.py
tspace/server/config/default.yml
tspace/server/constants.py
tspace/server/galaxy.py
tspace/server/graph.py
tspace/server/models.py
tspace/server/moves.py
tspace/server/server.py
tspace/server/util.py
tspace/server/web.py
tspace/server_app.py
terminal_space-0.2.0.dist-info/RECORD
