Metadata-Version: 2.1
Name: terminal-space
Version: 0.2.0
Summary: A text-based space trading game
Author-Email: Don Brown <mrdon@twdata.org>
License: APLv2
Requires-Python: <3.13,>=3.12
Requires-Dist: aiohttp>=3.5.4
Requires-Dist: colorclass>=2.0.0
Requires-Dist: networkx>=1.9.1
Requires-Dist: tabulate>=0.7.5
Requires-Dist: prompt-toolkit>=2.0.9
Requires-Dist: terminaltexteffects>=0.10.1
Requires-Dist: pillow>=10.3.0
